pyodide_html/__init__.py
pyodide_html-0.1.0.dist-info/LICENSE
pyodide_html-0.1.0.dist-info/METADATA
pyodide_html-0.1.0.dist-info/WHEEL
pyodide_html-0.1.0.dist-info/top_level.txt
pyodide_html-0.1.0.dist-info/RECORD
