Metadata-Version: 2.1
Name: pyodide-html
Version: 0.1.0
Summary: HTML elements for pyodide, implemented as Python functions
Home-page: https://github.com/xhlulu/pyodide-html
Author: Xing Han Lu
Author-email: github@xinghanlu.com
License: UNKNOWN
Platform: UNKNOWN
Classifier: Programming Language :: Python :: 3
Classifier: License :: OSI Approved :: MIT License
Classifier: Operating System :: OS Independent
Requires-Python: >=3.6
License-File: LICENSE
